{
  "mat.27.37": {
    "analytics": {
      "thisVerse": {
        "dict": {
          "eng": {
            "greek-2532": "And",
            "greek-2007": "they put up",
            "greek-1883": "over",
            "greek-3588": "of the",
            "greek-2776": "head",
            "greek-846": "of Him",
            "greek-156": "accusation",
            "greek-1125": "written",
            "greek-3778": "This",
            "greek-2076": "is",
            "greek-2424": "Jesus",
            "greek-935": "King",
            "greek-2453": "Jews",
            "": null
          },
          "cht": {
            "greek-2007": "安",
            "greek-1883": "以上",
            "greek-2776": "頭",
            "greek-846": "他的",
            "greek-156": "罪狀",
            "greek-1125": "寫著",
            "greek-3778": "這",
            "greek-2076": "是",
            "greek-2424": "耶穌",
            "greek-935": "的王",
            "greek-2453": "猶太人"
          }
        }
      },
      "translations": {
        "hebrew-7218": "greek-2776",
        "hebrew-3789": "greek-1125",
        "hebrew-4428": "greek-935",
        "hebrew-3064": "greek-2453"
      },
      "crossRefs": [
        {
          "totalScore": 6.327296856461155,
          "anchors": {
            "greek-2007": 2.6924581556670724,
            "greek-1125": 0.9423805451270103
          },
          "verseKey": "rev.22.18",
          "nasb": "I testify to everyone who hears the words of the prophecy of this book: if anyone adds to them, God will add to him the plagues which are written in this book;",
          "words": [
            {
              "id": "greek-191",
              "cht": "我向一切聽見"
            },
            {
              "id": "greek-5127",
              "cht": "這"
            },
            {
              "id": "greek-975",
              "cht": "書"
            },
            {
              "id": "greek-3056",
              "cht": "上預言"
            },
            {
              "id": "greek-3956",
              "cht": "的"
            },
            {
              "id": "greek-4828",
              "cht": "作見證",
              "punct_cht": "，"
            },
            {
              "id": "greek-1437",
              "cht": "若有"
            },
            {
              "id": "greek-5100",
              "cht": "人"
            },
            {
              "id": "greek-5023",
              "cht": "在這"
            },
            {
              "id": "greek-4314",
              "cht": "預言上"
            },
            {
              "id": "greek-2007",
              "cht": "加添"
            },
            {
              "id": "",
              "cht": "甚麼",
              "punct_cht": "，"
            },
            {
              "id": "greek-2316",
              "cht": "神"
            },
            {
              "id": "greek-1125",
              "cht": "必將寫"
            },
            {
              "id": "greek-5129",
              "cht": "在這"
            },
            {
              "id": "greek-975",
              "cht": "書"
            },
            {
              "id": "greek-1722",
              "cht": "上"
            },
            {
              "id": "greek-4127",
              "cht": "的災禍"
            },
            {
              "id": "greek-2007",
              "cht": "加"
            },
            {
              "id": "greek-846",
              "cht": "在他"
            },
            {
              "id": "greek-1909",
              "cht": "身上",
              "punct_cht": "；"
            }
          ]
        },
        {
          "totalScore": 5.172007876895164,
          "anchors": {
            "greek-156": 3.6363404553480576,
            "greek-935": 0.4103064360103035,
            "greek-2453": 1.1253609855368032
          },
          "verseKey": "mrk.15.26",
          "nasb": "The inscription of the charge against Him read, “THE KING OF THE JEWS.”",
          "words": [
            {
              "id": "greek-846",
              "cht": "在上面有他的"
            },
            {
              "id": "greek-156",
              "cht": "罪"
            },
            {
              "id": "greek-1923",
              "cht": "狀",
              "punct_cht": "，"
            },
            {
              "id": "greek-1924",
              "cht": "寫"
            },
            {
              "id": "greek-2258",
              "cht": "的是",
              "punct_cht": "："
            },
            {
              "id": "greek-2453",
              "cht": "猶太人"
            },
            {
              "id": "greek-935",
              "cht": "的王",
              "punct_cht": "。"
            }
          ]
        },
        {
          "totalScore": 5.1390763737580265,
          "anchors": {
            "greek-1125": 0.9423805451270103,
            "greek-935": 0.4103064360103035,
            "greek-2453": 1.1253609855368032
          },
          "verseKey": "jhn.19.21",
          "nasb": "So the chief priests of the Jews were saying to Pilate, “Do not write, ‘The King of the Jews’; but that He said, ‘I am King of the Jews.’ ”",
          "words": [
            {
              "id": "greek-2453",
              "cht": "猶太人"
            },
            {
              "id": "greek-749",
              "cht": "的祭司長"
            },
            {
              "id": "greek-3767",
              "cht": "就"
            },
            {
              "id": "greek-4091",
              "cht": "對彼拉多"
            },
            {
              "id": "greek-3004",
              "cht": "說",
              "punct_cht": "："
            },
            {
              "id": "greek-3361",
              "cht": "不要"
            },
            {
              "id": "greek-1125",
              "cht": "寫"
            },
            {
              "id": "greek-2453",
              "cht": "猶太人"
            },
            {
              "id": "greek-935",
              "cht": "的王",
              "punct_cht": "，"
            },
            {
              "id": "greek-3754",
              "cht": "要寫"
            },
            {
              "id": "greek-1565",
              "cht": "他自己"
            },
            {
              "id": "greek-2036",
              "cht": "說",
              "punct_cht": "："
            },
            {
              "id": "greek-1510",
              "cht": "我是"
            },
            {
              "id": "greek-2453",
              "cht": "猶太人"
            },
            {
              "id": "greek-935",
              "cht": "的王",
              "punct_cht": "。"
            }
          ]
        },
        {
          "totalScore": 5.1039973339297955,
          "anchors": {
            "greek-2007": 2.6924581556670724,
            "greek-2776": 0.8758717567156162,
            "greek-935": 0.4103064360103035,
            "greek-2453": 1.1253609855368032
          },
          "verseKey": "mat.27.29",
          "nasb": "And after twisting together a crown of thorns, they put it on His head, and a reed in His right hand; and they knelt down before Him and mocked Him, saying, “Hail, King of the Jews!”",
          "words": [
            {
              "id": "greek-1537",
              "cht": "用"
            },
            {
              "id": "greek-173",
              "cht": "荊棘"
            },
            {
              "id": "greek-4120",
              "cht": "編做"
            },
            {
              "id": "greek-4735",
              "cht": "冠冕",
              "punct_cht": "，"
            },
            {
              "id": "greek-2007",
              "cht": "戴"
            },
            {
              "id": "greek-846",
              "cht": "在他"
            },
            {
              "id": "greek-2776",
              "cht": "頭"
            },
            {
              "id": "greek-1909",
              "cht": "上",
              "punct_cht": "，"
            },
            {
              "id": "greek-2563",
              "cht": "拿一根葦子"
            },
            {
              "id": "greek-846",
              "cht": "放在他"
            },
            {
              "id": "greek-1188",
              "cht": "右手"
            },
            {
              "id": "greek-1909",
              "cht": "裡",
              "punct_cht": "，"
            },
            {
              "id": "greek-1120",
              "cht": "跪"
            },
            {
              "id": "greek-846",
              "cht": "在他"
            },
            {
              "id": "greek-1715",
              "cht": "面前",
              "punct_cht": "，"
            },
            {
              "id": "greek-1702",
              "cht": "戲弄"
            },
            {
              "id": "greek-846",
              "cht": "他",
              "punct_cht": "，"
            },
            {
              "id": "greek-3004",
              "cht": "說",
              "punct_cht": "："
            },
            {
              "id": "greek-5463",
              "cht": "恭喜",
              "punct_cht": "，"
            },
            {
              "id": "greek-2453",
              "cht": "猶太人"
            },
            {
              "id": "greek-935",
              "cht": "的王"
            },
            {
              "id": "",
              "cht": "啊",
              "punct_cht": "！"
            }
          ]
        },
        {
          "totalScore": 4.761701440884861,
          "anchors": {
            "greek-156": 3.6363404553480576,
            "greek-2453": 1.1253609855368032
          },
          "verseKey": "jhn.18.38",
          "nasb": "Pilate *said to Him, “What is truth?” And when he had said this, he went out again to the Jews and *said to them, “I find no guilt in Him.",
          "words": [
            {
              "id": "greek-846",
              "cht": "彼拉多"
            },
            {
              "id": "greek-3004",
              "cht": "說",
              "punct_cht": "："
            },
            {
              "id": "greek-225",
              "cht": "真理"
            },
            {
              "id": "greek-2076",
              "cht": "是"
            },
            {
              "id": "greek-5101",
              "cht": "甚麼"
            },
            {
              "id": "",
              "cht": "呢",
              "punct_cht": "？"
            },
            {
              "id": "greek-2036",
              "cht": "說了"
            },
            {
              "id": "greek-5124",
              "cht": "這話",
              "punct_cht": "，"
            },
            {
              "id": "greek-3825",
              "cht": "又"
            },
            {
              "id": "greek-1831",
              "cht": "出來"
            },
            {
              "id": "greek-4314",
              "cht": "到"
            },
            {
              "id": "greek-2453",
              "cht": "猶太人"
            },
            {
              "id": "",
              "cht": "那裡",
              "punct_cht": "，"
            },
            {
              "id": "greek-846",
              "cht": "對他們"
            },
            {
              "id": "greek-3004",
              "cht": "說",
              "punct_cht": "："
            },
            {
              "id": "greek-1473",
              "cht": "我"
            },
            {
              "id": "greek-2147",
              "cht": "查"
            },
            {
              "id": "greek-3762",
              "cht": "不出"
            },
            {
              "id": "greek-846",
              "cht": "他"
            },
            {
              "id": "greek-156",
              "cht": "有甚麼罪"
            },
            {
              "id": "",
              "cht": "來",
              "punct_cht": "。"
            }
          ]
        },
        {
          "totalScore": 4.651347819832038,
          "anchors": {
            "greek-1125": 0.9423805451270103,
            "greek-935": 0.4103064360103035,
            "greek-2453": 1.1253609855368032
          },
          "verseKey": "est.8.8",
          "nasb": "Now you write to the Jews as you see fit, in the king’s name, and seal it with the king’s signet ring; for a decree which is written in the name of the king and sealed with the king’s signet ring may not be revoked.”",
          "words": [
            {
              "id": "hebrew-859",
              "cht": "現在你們"
            },
            {
              "id": "hebrew-5869",
              "cht": "可以隨"
            },
            {
              "id": "hebrew-2896",
              "cht": "意"
            },
            {
              "id": "hebrew-4428",
              "cht": "奉王"
            },
            {
              "id": "hebrew-8034",
              "cht": "的名"
            },
            {
              "id": "hebrew-3789",
              "cht": "寫"
            },
            {
              "id": "hebrew-5921",
              "cht": "諭旨給"
            },
            {
              "id": "hebrew-3064",
              "cht": "猶大人",
              "punct_cht": "，"
            },
            {
              "id": "hebrew-4428",
              "cht": "用王"
            },
            {
              "id": "hebrew-2885",
              "cht": "的戒指"
            },
            {
              "id": "hebrew-2856",
              "cht": "蓋印",
              "punct_cht": "；"
            },
            {
              "id": "hebrew-3588",
              "cht": "因為"
            },
            {
              "id": "hebrew-4428",
              "cht": "奉王"
            },
            {
              "id": "hebrew-8034",
              "cht": "名"
            },
            {
              "id": "hebrew-834",
              "cht": "所"
            },
            {
              "id": "hebrew-3789",
              "cht": "寫、"
            },
            {
              "id": "hebrew-4428",
              "cht": "用王"
            },
            {
              "id": "hebrew-2885",
              "cht": "戒指"
            },
            {
              "id": "hebrew-2856",
              "cht": "蓋印"
            },
            {
              "id": "hebrew-3791",
              "cht": "的諭旨",
              "punct_cht": "，"
            },
            {
              "id": "hebrew-369",
              "cht": "人都不能"
            },
            {
              "id": "hebrew-7725",
              "cht": "廢除",
              "punct_cht": "。」"
            }
          ]
        },
        {
          "totalScore": 4.2410413838217345,
          "anchors": {
            "greek-1125": 0.9423805451270103,
            "greek-935": 0.4103064360103035,
            "greek-2453": 1.1253609855368032
          },
          "verseKey": "est.8.5",
          "nasb": "Then she said, “If it pleases the king and if I have found favor before him and the matter seems proper to the king and I am pleasing in his sight, let it be written to revoke the letters devised by Haman, the son of Hammedatha the Agagite, which he wrote to destroy the Jews who are in all the king’s provinces.",
          "words": [
            {
              "id": "hebrew-559",
              "cht": "說",
              "punct_cht": "：「"
            },
            {
              "id": "hebrew-91",
              "cht": "亞甲族"
            },
            {
              "id": "hebrew-4099",
              "cht": "哈米大他"
            },
            {
              "id": "hebrew-1121",
              "cht": "的兒子"
            },
            {
              "id": "hebrew-3789",
              "cht": "哈曼設謀傳旨",
              "punct_cht": "，"
            },
            {
              "id": "hebrew-853",
              "cht": "要殺滅"
            },
            {
              "id": "hebrew-4428",
              "cht": "在王"
            },
            {
              "id": "hebrew-3605",
              "cht": "各"
            },
            {
              "id": "hebrew-4082",
              "cht": "省"
            },
            {
              "id": "hebrew-834",
              "cht": "的"
            },
            {
              "id": "hebrew-3064",
              "cht": "猶大人",
              "punct_cht": "。"
            },
            {
              "id": "hebrew-5921",
              "cht": "現今"
            },
            {
              "id": "hebrew-4428",
              "cht": "王"
            },
            {
              "id": "hebrew-518",
              "cht": "若"
            },
            {
              "id": "hebrew-2896",
              "cht": "願意",
              "punct_cht": "，"
            },
            {
              "id": "hebrew-518",
              "cht": "我若"
            },
            {
              "id": "hebrew-6440",
              "cht": "在王眼前"
            },
            {
              "id": "hebrew-4672",
              "cht": "蒙"
            },
            {
              "id": "hebrew-2580",
              "cht": "恩",
              "punct_cht": "，"
            },
            {
              "id": "hebrew-4428",
              "cht": "王"
            },
            {
              "id": "hebrew-1697",
              "cht": "若以"
            },
            {
              "id": "hebrew-3787",
              "cht": "為美",
              "punct_cht": "，"
            },
            {
              "id": "hebrew-2896",
              "cht": "若喜悅"
            },
            {
              "id": "hebrew-589",
              "cht": "我",
              "punct_cht": "，"
            },
            {
              "id": "hebrew-3789",
              "cht": "請王另下"
            },
            {
              "id": "",
              "cht": "旨意",
              "punct_cht": "，"
            },
            {
              "id": "hebrew-853",
              "cht": "廢除"
            },
            {
              "id": "hebrew-2001",
              "cht": "哈曼"
            },
            {
              "id": "hebrew-834",
              "cht": "所"
            },
            {
              "id": "hebrew-4284",
              "cht": "傳"
            },
            {
              "id": "hebrew-5612",
              "cht": "的那旨意",
              "punct_cht": "。"
            }
          ]
        },
        {
          "totalScore": 4.068114133362667,
          "anchors": {
            "greek-1125": 0.9423805451270103,
            "greek-2424": 0.6476856215615396,
            "greek-935": 0.4103064360103035,
            "greek-2453": 1.1253609855368032
          },
          "verseKey": "jhn.19.19",
          "nasb": "Pilate also wrote an inscription and put it on the cross. It was written, “JESUS THE NAZARENE, THE KING OF THE JEWS.”",
          "words": [
            {
              "id": "greek-4091",
              "cht": "彼拉多"
            },
            {
              "id": "greek-1161",
              "cht": "又"
            },
            {
              "id": "greek-1125",
              "cht": "用牌子寫了"
            },
            {
              "id": "greek-5102",
              "cht": "一個名號",
              "punct_cht": "，"
            },
            {
              "id": "greek-5087",
              "cht": "安"
            },
            {
              "id": "greek-1909",
              "cht": "在"
            },
            {
              "id": "greek-4716",
              "cht": "十字架"
            },
            {
              "id": "",
              "cht": "上",
              "punct_cht": "，"
            },
            {
              "id": "greek-1125",
              "cht": "寫的"
            },
            {
              "id": "greek-2258",
              "cht": "是",
              "punct_cht": "："
            },
            {
              "id": "greek-2453",
              "cht": "猶太人"
            },
            {
              "id": "greek-935",
              "cht": "的王",
              "punct_cht": "，"
            },
            {
              "id": "greek-3480",
              "cht": "拿撒勒人"
            },
            {
              "id": "greek-2424",
              "cht": "耶穌",
              "punct_cht": "。"
            }
          ]
        },
        {
          "totalScore": 3.6363404553480576,
          "anchors": {
            "greek-156": 3.6363404553480576
          },
          "verseKey": "tit.1.13",
          "nasb": "This testimony is true. For this reason reprove them severely so that they may be sound in the faith,",
          "words": [
            {
              "id": "greek-3778",
              "cht": "這個"
            },
            {
              "id": "greek-3141",
              "cht": "見證"
            },
            {
              "id": "greek-2076",
              "cht": "是"
            },
            {
              "id": "greek-227",
              "cht": "真的",
              "punct_cht": "。"
            },
            {
              "id": "greek-1223",
              "cht": "所以",
              "punct_cht": "，"
            },
            {
              "id": "greek-664",
              "cht": "你要嚴嚴的"
            },
            {
              "id": "greek-1651",
              "cht": "責備"
            },
            {
              "id": "greek-846",
              "cht": "他們",
              "punct_cht": "，"
            },
            {
              "id": "greek-2443",
              "cht": "使"
            },
            {
              "id": "greek-4102",
              "cht": "他們在真道"
            },
            {
              "id": "greek-1722",
              "cht": "上"
            },
            {
              "id": "greek-5198",
              "cht": "純全無疵",
              "punct_cht": "，"
            }
          ]
        },
        {
          "totalScore": 3.6363404553480576,
          "anchors": {
            "greek-156": 3.6363404553480576
          },
          "verseKey": "mat.19.10",
          "nasb": "The disciples *said to Him, “If the relationship of the man with his wife is like this, it is better not to marry.”",
          "words": [
            {
              "id": "greek-3101",
              "cht": "門徒"
            },
            {
              "id": "greek-846",
              "cht": "對耶穌"
            },
            {
              "id": "greek-3004",
              "cht": "說",
              "punct_cht": "："
            },
            {
              "id": "greek-444",
              "cht": "人"
            },
            {
              "id": "greek-3326",
              "cht": "和"
            },
            {
              "id": "greek-1135",
              "cht": "妻子"
            },
            {
              "id": "greek-2076",
              "cht": "既是"
            },
            {
              "id": "greek-3779",
              "cht": "這樣",
              "punct_cht": "，"
            },
            {
              "id": "greek-3756",
              "cht": "倒不如不"
            },
            {
              "id": "greek-1060",
              "cht": "娶",
              "punct_cht": "。"
            }
          ]
        }
      ]
    },
    "interpretations": {
      "dde": {
        "content": [
          {
            "verse": "mat.27.27-56",
            "paragraphs": [
              "Ｃ耶穌被釘十字架（二十七27～56）"
            ]
          },
          {
            "verse": "mat.27.32-44",
            "paragraphs": [
              "ii.耶穌被釘十字架（二十七32～44）",
              "第22～26節已為本段所要描述的可怕事件作了準備。猶太律法從不允許將人釘十字架處死，但這種刑罰在巴勒斯坦卻從公元前一世紀就已普遍執行，是羅馬人專用來懲治政治叛亂份子和暴徒的，執行時盡量使眾人圍觀，以起殺一儆百的效用327。詳述酷刑給犯人帶來的痛苦和犯人死前的慘狀並不困難，基督徒在傳道時常常不厭其煩地講述一些細節，可是福音書的作者們卻沒有這樣做，馬太更是一筆帶過，僅用了一個分詞表示耶穌已被他們釘在十字架上了（35a節）。他更註意的是事件本身的意義，所以他再次著重寫了戲弄的部分，就如第27～31節那樣，但這次已不是外邦人，而是猶太人自己在汙辱譏誚他們的“王”了。更為驚人的是，在這段難以想像的情節中，一些基督論中最高的稱號都以醒目的形式集中地被提出來，如：猶太人的王、建造聖殿者、神的兒子（兩次）和以色列的王等。他們用這些稱號極盡其譏諷嘲弄之能事，但事實上卻一而再、再而三地強調這些稱號，因為耶穌神聖而高貴的使命，本來就是註定要在受汙辱和被釘十字架中完成。一位彌賽亞卻遭十字架上處死的命運，這種震撼人心的矛盾現象在本段的記述裏強烈表明出來。"
            ]
          },
          {
            "verse": "mat.27.37",
            "paragraphs": [
              "37.寫成的罪狀（或稱罪名牌）通常是在犯人被押往刑場時由人在他前邊舉著，或是掛在犯人的脖子上，然後安在十字架上，以起殺一儆百之作用。猶太人的王在這裏自然是諷刺的，是對那些要作解放者的人們發出的警告；不過馬太無疑是希望他的讀者能透過表面的諷刺去理解，耶穌是透過祂的死而作王這一似非而是的事實。在他頭上說明耶穌的十字架是傳統的十字形的，不是常用的丁字形的。"
            ]
          }
        ],
        "title": "丁道爾聖經註釋",
        "author": "丁道爾"
      },
      "matangna": {
        "content": [
          {
            "verse": "mat.27.32-44",
            "paragraphs": [
              "十六．王被釘十字架（二七32～44）"
            ]
          },
          {
            "verse": "mat.27.37",
            "paragraphs": [
              "二七37他們在基督的頭以上安了一個牌子。這是猶太人的王耶穌。四福音所用的字眼並不一樣52。馬可這樣寫：“猶太人的王。”（可一五26）路加這樣寫：“這是猶太人的王。”（路二三38）約翰則這樣寫：“猶太人的王、拿撒勒人耶穌。”（約一九19）祭司長抗議說牌子上不可以記述事實，只可寫被告所認的罪狀。可是，彼拉多的權力駁回了他們。所有人都清楚看見牌子上所寫，因為用了希伯來、羅馬和希臘的文字（約一九19～22）。"
            ]
          }
        ],
        "title": "馬唐納註釋",
        "author": "馬唐納"
      }
    },
    "versions": {
      "ccb": {
        "version_id": "CCB",
        "version_name": "圣经当代译本",
        "lang": "chs",
        "text": "他们在祂头顶上挂了一个牌子，上面写着祂的罪状：“这是犹太人的王耶稣”。"
      },
      "cnv": {
        "version_id": "CNV",
        "version_name": "新譯本",
        "lang": "cht",
        "text": "他們在耶穌的頭以上，釘了一塊牌子，寫著他的罪狀：“這是猶太人的王耶穌”。"
      },
      "csbs": {
        "version_id": "CSBS",
        "version_name": "中文标准译本",
        "lang": "chs",
        "text": "又在他的头上方，安了他的罪状牌，上面写道：“这是耶稣，犹太人的王。”"
      },
      "cunp": {
        "version_id": "CUNP",
        "version_name": "和合本新標點（神版）",
        "lang": "cht",
        "text": "在他頭以上安一個牌子，寫着他的罪狀，說：「這是猶太人的王耶穌。」"
      },
      "esv": {
        "version_id": "ESV",
        "version_name": "English Standard Version",
        "lang": "en",
        "text": "And over his head they put the charge against him, which read, “This is Jesus, the King of the Jews.”"
      },
      "nasb": {
        "version_id": "NASB",
        "version_name": "New American Standard Bible",
        "lang": "en",
        "text": "And above His head they put up the charge against Him which read, “THIS IS JESUS THE KING OF THE JEWS.”"
      },
      "niv": {
        "version_id": "NIV",
        "version_name": "New International Version",
        "lang": "en",
        "text": "Above his head they placed the written charge against him: this is jesus, the king of the jews."
      },
      "nkjv": {
        "version_id": "NKJV",
        "version_name": "New King James Version",
        "lang": "en",
        "text": "And they put up over His head the accusation written against Him: THIS IS JESUS THE KING OF THE JEWS."
      },
      "nlt": {
        "version_id": "NLT",
        "version_name": "New Living Translation",
        "lang": "en",
        "text": "A sign was fastened above Jesus’ head, announcing the charge against him. It read: “This is Jesus, the King of the Jews.”"
      }
    },
    "words": [
      {
        "id": "greek-2532",
        "translit": "kai",
        "lang": "greek",
        "greek": "καὶ",
        "pos": "Conj",
        "eng": "And",
        "origin_simp": "και"
      },
      {
        "id": "greek-2007",
        "translit": "epethēkan",
        "lang": "greek",
        "greek": "ἐπέθηκαν",
        "pos": "V-AIA-3P",
        "eng": "they put up",
        "origin_simp": "επεθηκαν",
        "index_cht": 3,
        "cht": "安"
      },
      {
        "id": "greek-1883",
        "translit": "epanō",
        "lang": "greek",
        "greek": "ἐπάνω",
        "pos": "Prep",
        "eng": "over",
        "origin_simp": "επανω",
        "index_cht": 2,
        "cht": "以上"
      },
      {
        "id": "greek-3588",
        "translit": "tēs",
        "lang": "greek",
        "greek": "τῆς",
        "pos": "Art-GFS",
        "eng": "the",
        "origin_simp": "της"
      },
      {
        "id": "greek-2776",
        "translit": "kephalēs",
        "lang": "greek",
        "greek": "κεφαλῆς",
        "pos": "N-GFS",
        "eng": "head",
        "origin_simp": "κεφαλης",
        "index_cht": 1,
        "cht": "頭"
      },
      {
        "id": "greek-846",
        "translit": "autou",
        "lang": "greek",
        "greek": "αὐτοῦ",
        "pos": "PPro-GM3S",
        "eng": "of Him",
        "origin_simp": "αυτου",
        "index_cht": 0,
        "cht": "在他"
      },
      {
        "id": "greek-3588",
        "translit": "tēn",
        "lang": "greek",
        "greek": "τὴν",
        "pos": "Art-AFS",
        "eng": "the",
        "origin_simp": "την"
      },
      {
        "id": "greek-156",
        "translit": "aitian",
        "lang": "greek",
        "greek": "αἰτίαν",
        "pos": "N-AFS",
        "eng": "accusation",
        "origin_simp": "αιτιαν",
        "index_cht": 7,
        "cht": "罪狀"
      },
      {
        "id": "greek-846",
        "translit": "autou",
        "lang": "greek",
        "greek": "αὐτοῦ",
        "pos": "PPro-GM3S",
        "eng": "of Him",
        "origin_simp": "αυτου",
        "index_cht": 6,
        "cht": "他的"
      },
      {
        "id": "greek-1125",
        "translit": "gegrammenēn",
        "lang": "greek",
        "greek": "γεγραμμένην",
        "pos": "V-RPM/P-AFS",
        "punct": ":",
        "eng": "written",
        "origin_simp": "γεγραμμενην",
        "index_cht": 5,
        "cht": "寫著"
      },
      {
        "id": "greek-3778",
        "translit": "HOUTOS",
        "lang": "greek",
        "greek": "ΟΥΤΟΣ*",
        "pos": "DPro-NMS",
        "eng": "This",
        "origin_simp": "ουτος",
        "index_cht": 9,
        "cht": "這"
      },
      {
        "id": "greek-2076",
        "translit": "ESTIN",
        "lang": "greek",
        "greek": "ΕΣΤΙΝ",
        "pos": "V-PIA-3S",
        "eng": "is",
        "origin_simp": "εστιν",
        "index_cht": 10,
        "cht": "是"
      },
      {
        "id": "greek-2424",
        "translit": "IĒSOUS",
        "lang": "greek",
        "greek": "ΙΗΣΟΥΣ",
        "pos": "N-NMS",
        "punct": ",",
        "eng": "Jesus",
        "origin_simp": "ιησους",
        "index_cht": 13,
        "cht": "耶穌",
        "punct_cht": "。"
      },
      {
        "id": "greek-3588",
        "translit": "HO",
        "lang": "greek",
        "greek": "Ο*",
        "pos": "Art-NMS",
        "eng": "the",
        "origin_simp": "ο*"
      },
      {
        "id": "greek-935",
        "translit": "BASILEUS",
        "lang": "greek",
        "greek": "ΒΑΣΙΛΕΥΣ",
        "pos": "N-NMS",
        "eng": "King",
        "origin_simp": "βασιλευς",
        "index_cht": 12,
        "cht": "的王"
      },
      {
        "id": "greek-3588",
        "translit": "TŌN",
        "lang": "greek",
        "greek": "ΤΩΝ",
        "pos": "Art-GMP",
        "eng": "of the",
        "origin_simp": "των"
      },
      {
        "id": "greek-2453",
        "translit": "IOUDAIŌN",
        "lang": "greek",
        "greek": "ΙΟΥΔΑΙΩΝ",
        "pos": "Adj-GMP",
        "punct": ".",
        "eng": "Jews",
        "origin_simp": "ιουδαιων",
        "index_cht": 11,
        "cht": "猶太人"
      },
      {
        "id": "",
        "origin_simp": "",
        "index_cht": 4,
        "cht": "一個牌子",
        "punct_cht": "，"
      },
      {
        "id": "",
        "origin_simp": "",
        "index_cht": 8,
        "cht": "說",
        "punct_cht": "，："
      }
    ]
  }
}
