{
  "phm.1.7": {
    "analytics": {
      "thisVerse": {
        "dict": {
          "greek-5479": "Joy",
          "greek-1063": "for",
          "greek-4183": "great",
          "greek-2192": "I have",
          "greek-2532": "and",
          "greek-3874": "encouragement",
          "greek-1909": "by occasion of",
          "greek-3588": "of the",
          "greek-26": "love",
          "greek-4771": "you",
          "greek-3754": "because",
          "greek-4698": "hearts",
          "greek-40": "saints",
          "greek-373": "have been refreshed",
          "greek-1223": "by",
          "greek-80": "brother"
        }
      },
      "crossRefs": [
        {
          "totalScore": 10.34710452992041,
          "anchors": {
            "greek-4698": 4.758842454566098,
            "greek-373": 4.576110205744392,
            "greek-80": 1.0121518696099194
          },
          "verseKey": "phm.1.20",
          "cunp": "兄弟啊，望你使我在主裏因你得快樂，並望你使我的心在基督裏得暢快。",
          "words": [
            {
              "id": "greek-3483",
              "eng": "Yes",
              "punct": ","
            },
            {
              "id": "greek-80",
              "eng": "brother",
              "punct": ","
            },
            {
              "id": "greek-1473",
              "eng": "I"
            },
            {
              "id": "greek-4771",
              "eng": "from you"
            },
            {
              "id": "greek-3685",
              "eng": "may have profit"
            },
            {
              "id": "greek-1722",
              "eng": "in"
            },
            {
              "id": "greek-2962",
              "eng": "[the] Lord",
              "punct": "."
            },
            {
              "id": "greek-373",
              "eng": "Refresh"
            },
            {
              "id": "greek-1473",
              "eng": "my"
            },
            {
              "id": "greek-3588",
              "eng": "-"
            },
            {
              "id": "greek-4698",
              "eng": "heart"
            },
            {
              "id": "greek-1722",
              "eng": "in"
            },
            {
              "id": "greek-5547",
              "eng": "Christ",
              "punct": "."
            }
          ]
        },
        {
          "totalScore": 9.887384366047806,
          "anchors": {
            "greek-5479": 2.234830709167281,
            "greek-3874": 3.0764434511361327,
            "greek-373": 4.576110205744392
          },
          "verseKey": "2co.7.13",
          "cunp": "故此，我們得了安慰。 並且在安慰之中，因你們眾人使提多心裏暢快歡喜，我們就更加歡喜了。",
          "words": [
            {
              "id": "greek-1223",
              "eng": "On account of"
            },
            {
              "id": "greek-3778",
              "eng": "this",
              "punct": ","
            },
            {
              "id": "greek-3870",
              "eng": "we have been comforted",
              "punct": "."
            },
            {
              "id": "greek-1909",
              "eng": "Besides"
            },
            {
              "id": "greek-1161",
              "eng": "now"
            },
            {
              "id": "greek-3588",
              "eng": "the"
            },
            {
              "id": "greek-3874",
              "eng": "comfort"
            },
            {
              "id": "greek-1473",
              "eng": "of us",
              "punct": ","
            },
            {
              "id": "greek-4057",
              "eng": "the more abundantly"
            },
            {
              "id": "greek-3123",
              "eng": "rather"
            },
            {
              "id": "greek-5463",
              "eng": "we have rejoiced"
            },
            {
              "id": "greek-1909",
              "eng": "at"
            },
            {
              "id": "greek-3588",
              "eng": "the"
            },
            {
              "id": "greek-5479",
              "eng": "joy"
            },
            {
              "id": "greek-5103",
              "eng": "of Titus",
              "punct": ","
            },
            {
              "id": "greek-3754",
              "eng": "because"
            },
            {
              "id": "greek-373",
              "eng": "has been refreshed"
            },
            {
              "id": "greek-3588",
              "eng": "the"
            },
            {
              "id": "greek-4151",
              "eng": "spirit"
            },
            {
              "id": "greek-846",
              "eng": "of him"
            },
            {
              "id": "greek-575",
              "eng": "by"
            },
            {
              "id": "greek-3956",
              "eng": "all"
            },
            {
              "id": "greek-4771",
              "eng": "of you",
              "punct": "."
            }
          ]
        },
        {
          "totalScore": 9.483911130662868,
          "anchors": {
            "greek-3874": 3.0764434511361327,
            "greek-26": 1.6486252249606381,
            "greek-4698": 4.758842454566098
          },
          "verseKey": "php.2.1",
          "cunp": "所以，在基督裏若有甚麼勸勉，愛心有甚麼安慰，聖靈有甚麼交通，心中有甚麼慈悲憐憫，",
          "words": [
            {
              "id": "greek-1487",
              "eng": "If [there is]"
            },
            {
              "id": "greek-5100",
              "eng": "any"
            },
            {
              "id": "greek-3767",
              "eng": "therefore"
            },
            {
              "id": "greek-3874",
              "eng": "encouragement"
            },
            {
              "id": "greek-1722",
              "eng": "in"
            },
            {
              "id": "greek-5547",
              "eng": "Christ",
              "punct": ","
            },
            {
              "id": "greek-1487",
              "eng": "if"
            },
            {
              "id": "greek-5100",
              "eng": "any"
            },
            {
              "id": "greek-3890",
              "eng": "comfort"
            },
            {
              "id": "greek-26",
              "eng": "of love",
              "punct": ","
            },
            {
              "id": "greek-1487",
              "eng": "if"
            },
            {
              "id": "greek-5100",
              "eng": "any"
            },
            {
              "id": "greek-2842",
              "eng": "fellowship"
            },
            {
              "id": "greek-4151",
              "eng": "of [the] Spirit",
              "punct": ","
            },
            {
              "id": "greek-1487",
              "eng": "if"
            },
            {
              "id": "greek-5100",
              "eng": "any"
            },
            {
              "id": "greek-4698",
              "eng": "affections"
            },
            {
              "id": "greek-2532",
              "eng": "and"
            },
            {
              "id": "greek-3628",
              "eng": "compassions",
              "punct": ","
            }
          ]
        },
        {
          "totalScore": 8.877818263549536,
          "anchors": {
            "greek-2192": 0.7290993572064405,
            "greek-26": 1.6486252249606381,
            "greek-4698": 4.758842454566098,
            "greek-80": 1.0121518696099194
          },
          "verseKey": "1jn.3.17",
          "cunp": "凡有世上財物的，看見弟兄窮乏，卻塞住憐恤的心，愛神的心怎能存在他裏面呢？",
          "words": [
            {
              "id": "greek-3739",
              "eng": "Whoever"
            },
            {
              "id": "greek-1161",
              "eng": "now"
            },
            {
              "id": "greek-302",
              "eng": "-"
            },
            {
              "id": "greek-2192",
              "eng": "might have"
            },
            {
              "id": "greek-3588",
              "eng": "the"
            },
            {
              "id": "greek-979",
              "eng": "goods"
            },
            {
              "id": "greek-3588",
              "eng": "of the"
            },
            {
              "id": "greek-2889",
              "eng": "world",
              "punct": ","
            },
            {
              "id": "greek-2532",
              "eng": "and"
            },
            {
              "id": "greek-2334",
              "eng": "might see"
            },
            {
              "id": "greek-3588",
              "eng": "the"
            },
            {
              "id": "greek-80",
              "eng": "brother"
            },
            {
              "id": "greek-846",
              "eng": "of him"
            },
            {
              "id": "greek-5532",
              "eng": "need"
            },
            {
              "id": "greek-2192",
              "eng": "having",
              "punct": ","
            },
            {
              "id": "greek-2532",
              "eng": "and"
            },
            {
              "id": "greek-2808",
              "eng": "might close up"
            },
            {
              "id": "greek-3588",
              "eng": "the"
            },
            {
              "id": "greek-4698",
              "eng": "heart"
            },
            {
              "id": "greek-846",
              "eng": "of him"
            },
            {
              "id": "greek-575",
              "eng": "from"
            },
            {
              "id": "greek-846",
              "eng": "him",
              "punct": ","
            },
            {
              "id": "greek-4459",
              "eng": "how"
            },
            {
              "id": "greek-3588",
              "eng": "the"
            },
            {
              "id": "greek-26",
              "eng": "love"
            },
            {
              "id": "greek-3588",
              "eng": "-"
            },
            {
              "id": "greek-2316",
              "eng": "of God"
            },
            {
              "id": "greek-3306",
              "eng": "abides"
            },
            {
              "id": "greek-1722",
              "eng": "in"
            },
            {
              "id": "greek-846",
              "eng": "him",
              "punct": "?"
            }
          ]
        },
        {
          "totalScore": 7.289517856458094,
          "anchors": {
            "greek-5479": 2.234830709167281,
            "greek-4183": 0.9891218480773403,
            "greek-3874": 3.0764434511361327
          },
          "verseKey": "2co.7.4",
          "cunp": "我大大地放膽，向你們說話；我因你們多多誇口，滿得安慰；我們在一切患難中分外地快樂。",
          "words": [
            {
              "id": "greek-4183",
              "eng": "Great [is]"
            },
            {
              "id": "greek-1473",
              "eng": "my"
            },
            {
              "id": "greek-3954",
              "eng": "boldness"
            },
            {
              "id": "greek-4314",
              "eng": "toward"
            },
            {
              "id": "greek-4771",
              "eng": "you",
              "punct": ";"
            },
            {
              "id": "greek-4183",
              "eng": "great"
            },
            {
              "id": "greek-1473",
              "eng": "my"
            },
            {
              "id": "greek-2746",
              "eng": "boasting"
            },
            {
              "id": "greek-5228",
              "eng": "on behalf of"
            },
            {
              "id": "greek-4771",
              "eng": "you",
              "punct": ";"
            },
            {
              "id": "greek-4137",
              "eng": "I have been filled"
            },
            {
              "id": "greek-3588",
              "eng": "-"
            },
            {
              "id": "greek-3874",
              "eng": "with encouragement",
              "punct": ";"
            },
            {
              "id": "greek-5248",
              "eng": "I overabound"
            },
            {
              "id": "greek-3588",
              "eng": "-"
            },
            {
              "id": "greek-5479",
              "eng": "with joy"
            },
            {
              "id": "greek-1909",
              "eng": "upon"
            },
            {
              "id": "greek-3956",
              "eng": "all"
            },
            {
              "id": "greek-3588",
              "eng": "the"
            },
            {
              "id": "greek-2347",
              "eng": "affliction"
            },
            {
              "id": "greek-1473",
              "eng": "of us",
              "punct": "."
            }
          ]
        },
        {
          "totalScore": 7.283453259105514,
          "anchors": {
            "greek-4183": 0.9891218480773403,
            "greek-2192": 0.7290993572064405,
            "greek-373": 4.576110205744392
          },
          "verseKey": "luk.12.19",
          "cunp": "然後要對我的靈魂說：靈魂哪，你有許多財物積存，可作多年的費用，只管安安逸逸地吃喝快樂吧！』",
          "words": [
            {
              "id": "greek-2532",
              "eng": "And"
            },
            {
              "id": "greek-2046",
              "eng": "I will say"
            },
            {
              "id": "greek-3588",
              "eng": "to the"
            },
            {
              "id": "greek-5590",
              "eng": "soul"
            },
            {
              "id": "greek-1473",
              "eng": "of me",
              "punct": ","
            },
            {
              "id": "greek-5590",
              "eng": "Soul",
              "punct": ","
            },
            {
              "id": "greek-2192",
              "eng": "you have"
            },
            {
              "id": "greek-4183",
              "eng": "many"
            },
            {
              "id": "greek-18",
              "eng": "good things"
            },
            {
              "id": "greek-2749",
              "eng": "laid up"
            },
            {
              "id": "greek-1519",
              "eng": "for"
            },
            {
              "id": "greek-2094",
              "eng": "years"
            },
            {
              "id": "greek-4183",
              "eng": "many",
              "punct": ";"
            },
            {
              "id": "greek-373",
              "eng": "take your rest",
              "punct": ";"
            },
            {
              "id": "greek-5315",
              "eng": "eat",
              "punct": ","
            },
            {
              "id": "greek-4095",
              "eng": "drink",
              "punct": ","
            },
            {
              "id": "greek-2165",
              "eng": "be merry",
              "punct": "."
            }
          ]
        },
        {
          "totalScore": 6.152886902272265,
          "anchors": {
            "greek-3874": 3.0764434511361327
          },
          "verseKey": "2co.1.6",
          "cunp": "我們受患難呢，是為叫你們得安慰，得拯救；我們得安慰呢，也是為叫你們得安慰；這安慰能叫你們忍受我們所受的那樣苦楚。",
          "words": [
            {
              "id": "greek-1535",
              "eng": "If"
            },
            {
              "id": "greek-1161",
              "eng": "however"
            },
            {
              "id": "greek-2346",
              "eng": "we are constricted",
              "punct": ","
            },
            {
              "id": "greek-5228",
              "eng": "[it is] for"
            },
            {
              "id": "greek-3588",
              "eng": "-"
            },
            {
              "id": "greek-4771",
              "eng": "your"
            },
            {
              "id": "greek-3874",
              "eng": "comfort"
            },
            {
              "id": "greek-2532",
              "eng": "and"
            },
            {
              "id": "greek-4991",
              "eng": "salvation",
              "punct": ";"
            },
            {
              "id": "greek-1535",
              "eng": "if"
            },
            {
              "id": "greek-3870",
              "eng": "we are encouraged",
              "punct": ","
            },
            {
              "id": "greek-5228",
              "eng": "[it is] for"
            },
            {
              "id": "greek-3588",
              "eng": "-"
            },
            {
              "id": "greek-4771",
              "eng": "your"
            },
            {
              "id": "greek-3874",
              "eng": "comfort",
              "punct": ","
            },
            {
              "id": "greek-3588",
              "eng": "-"
            },
            {
              "id": "greek-1754",
              "eng": "operating"
            },
            {
              "id": "greek-1722",
              "eng": "in"
            },
            {
              "id": "greek-5281",
              "eng": "[the] endurance"
            },
            {
              "id": "greek-3588",
              "eng": "of the"
            },
            {
              "id": "greek-846",
              "eng": "same"
            },
            {
              "id": "greek-3804",
              "eng": "sufferings"
            },
            {
              "id": "greek-3739",
              "eng": "that"
            },
            {
              "id": "greek-2532",
              "eng": "also"
            },
            {
              "id": "greek-1473",
              "eng": "we"
            },
            {
              "id": "greek-3958",
              "eng": "suffer",
              "punct": "."
            }
          ]
        },
        {
          "totalScore": 5.9587492079368936,
          "anchors": {
            "greek-4698": 4.758842454566098,
            "greek-40": 1.1999067533707957
          },
          "verseKey": "col.3.12",
          "cunp": "所以，你們既是神的選民，聖潔蒙愛的人，就要存憐憫、恩慈、謙虛、溫柔、忍耐的心。",
          "words": [
            {
              "id": "greek-1746",
              "eng": "Put on"
            },
            {
              "id": "greek-3767",
              "eng": "therefore",
              "punct": ","
            },
            {
              "id": "greek-5613",
              "eng": "as"
            },
            {
              "id": "greek-1588",
              "eng": "[the] elect"
            },
            {
              "id": "greek-3588",
              "eng": "-"
            },
            {
              "id": "greek-2316",
              "eng": "of God",
              "punct": ","
            },
            {
              "id": "greek-40",
              "eng": "holy"
            },
            {
              "id": "greek-2532",
              "eng": "and"
            },
            {
              "id": "greek-25",
              "eng": "beloved",
              "punct": ","
            },
            {
              "id": "greek-4698",
              "eng": "hearts"
            },
            {
              "id": "greek-3628",
              "eng": "of compassion",
              "punct": ","
            },
            {
              "id": "greek-5544",
              "eng": "kindness",
              "punct": ","
            },
            {
              "id": "greek-5012",
              "eng": "humility",
              "punct": ","
            },
            {
              "id": "greek-4240",
              "eng": "gentleness",
              "punct": ","
            },
            {
              "id": "greek-3115",
              "eng": "[and] patience",
              "punct": ";"
            }
          ]
        },
        {
          "totalScore": 5.674975032088355,
          "anchors": {
            "greek-2192": 0.7290993572064405,
            "greek-26": 1.6486252249606381
          },
          "verseKey": "1jn.4.16",
          "cunp": "神愛我們的心，我們也知道也信。 神就是愛；住在愛裏面的，就是住在神裏面，神也住在他裏面。",
          "words": [
            {
              "id": "greek-2532",
              "eng": "And"
            },
            {
              "id": "greek-1473",
              "eng": "we"
            },
            {
              "id": "greek-1097",
              "eng": "have come to know"
            },
            {
              "id": "greek-2532",
              "eng": "and"
            },
            {
              "id": "greek-4100",
              "eng": "have come to believe"
            },
            {
              "id": "greek-3588",
              "eng": "the"
            },
            {
              "id": "greek-26",
              "eng": "love"
            },
            {
              "id": "greek-3739",
              "eng": "that"
            },
            {
              "id": "greek-2192",
              "eng": "has"
            },
            {
              "id": "greek-3588",
              "eng": "-"
            },
            {
              "id": "greek-2316",
              "eng": "God"
            },
            {
              "id": "greek-1722",
              "eng": "as to"
            },
            {
              "id": "greek-1473",
              "eng": "us",
              "punct": "."
            },
            {
              "id": "greek-3588",
              "eng": "-"
            },
            {
              "id": "greek-2316",
              "eng": "God"
            },
            {
              "id": "greek-26",
              "eng": "love"
            },
            {
              "id": "greek-1510",
              "eng": "is",
              "punct": ","
            },
            {
              "id": "greek-2532",
              "eng": "and"
            },
            {
              "id": "greek-3588",
              "eng": "the [one]"
            },
            {
              "id": "greek-3306",
              "eng": "abiding"
            },
            {
              "id": "greek-1722",
              "eng": "in"
            },
            {
              "id": "greek-3588",
              "eng": "-"
            },
            {
              "id": "greek-26",
              "eng": "love",
              "punct": ","
            },
            {
              "id": "greek-1722",
              "eng": "in"
            },
            {
              "id": "greek-3588",
              "eng": "-"
            },
            {
              "id": "greek-2316",
              "eng": "God"
            },
            {
              "id": "greek-3306",
              "eng": "abides",
              "punct": ","
            },
            {
              "id": "greek-2532",
              "eng": "and"
            },
            {
              "id": "greek-3588",
              "eng": "-"
            },
            {
              "id": "greek-2316",
              "eng": "God"
            },
            {
              "id": "greek-1722",
              "eng": "in"
            },
            {
              "id": "greek-846",
              "eng": "him"
            },
            {
              "id": "greek-3306",
              "eng": "abides",
              "punct": "."
            }
          ]
        },
        {
          "totalScore": 5.674975032088355,
          "anchors": {
            "greek-2192": 0.7290993572064405,
            "greek-26": 1.6486252249606381
          },
          "verseKey": "1jn.4.18",
          "cunp": "愛裏沒有懼怕；愛既完全，就把懼怕除去。因為懼怕裏含着刑罰，懼怕的人在愛裏未得完全。",
          "words": [
            {
              "id": "greek-5401",
              "eng": "Fear"
            },
            {
              "id": "greek-3756",
              "eng": "no"
            },
            {
              "id": "greek-1510",
              "eng": "there is"
            },
            {
              "id": "greek-1722",
              "eng": "in"
            },
            {
              "id": "greek-3588",
              "eng": "-"
            },
            {
              "id": "greek-26",
              "eng": "love",
              "punct": ","
            },
            {
              "id": "greek-235",
              "eng": "but"
            },
            {
              "id": "greek-3588",
              "eng": "-"
            },
            {
              "id": "greek-5046",
              "eng": "perfect"
            },
            {
              "id": "greek-26",
              "eng": "love"
            },
            {
              "id": "greek-1854",
              "eng": "out"
            },
            {
              "id": "greek-906",
              "eng": "casts"
            },
            {
              "id": "greek-3588",
              "eng": "-"
            },
            {
              "id": "greek-5401",
              "eng": "fear",
              "punct": ","
            },
            {
              "id": "greek-3754",
              "eng": "because"
            },
            {
              "id": "greek-3588",
              "eng": "the"
            },
            {
              "id": "greek-5401",
              "eng": "fear"
            },
            {
              "id": "greek-2851",
              "eng": "punishment"
            },
            {
              "id": "greek-2192",
              "eng": "has",
              "punct": ";"
            },
            {
              "id": "greek-3588",
              "eng": "the [one]"
            },
            {
              "id": "greek-1161",
              "eng": "now"
            },
            {
              "id": "greek-5399",
              "eng": "fearing",
              "punct": ","
            },
            {
              "id": "greek-3756",
              "eng": "not"
            },
            {
              "id": "greek-5048",
              "eng": "has been perfected"
            },
            {
              "id": "greek-1722",
              "eng": "in"
            },
            {
              "id": "greek-3588",
              "eng": "-"
            },
            {
              "id": "greek-26",
              "eng": "love",
              "punct": "."
            }
          ]
        }
      ]
    },
    "interpretations": {
      "chenzhongdao": {
        "content": [
          {
            "verse": "phm.1.7",
            "paragraphs": [
              "7註意，保羅在16節也稱阿尼西母為弟兄。雖然腓利門是主人，阿尼西母是奴仆，但在保羅心中並無這些階級的分別，同樣看他們是親愛的弟兄。這種在基督裏都是弟兄的關系，實在是今日自由平等思想的重要基礎。保羅雖然不是專門改革社會制度的人，但福音被人接受的結果，卻使主人和奴仆實際上成了兄弟；並且這種屬靈的兄弟情份，比較肉身的兄弟關系更為密切，因為它不只是今世在主內的一種關系，更是在永世中永遠繼續下去的關系。",
              "保羅為腓利門的愛心大有快樂，他這種快樂本身也是出於愛心。因他如果不關懷腓利門，怎會為他快樂？在基督裏所享受的快樂，常是因自己愛主愛弟兄而有的。",
              "腓利門大概沒料想到，他在自己家中用愛心對待主內弟兄姊妹，為基督而行善，卻能使那遠在羅馬的保羅“大得安慰”。並且這種安慰，在保羅看來，實在比較說許多安慰話，甚或贈送許多禮物更為可貴。基督徒應當知道，我們現今在地上用愛心待人，也能使天上的基督心中暢快。",
              "“因眾聖徒的心從你得了暢快”，“暢快”原文anapepauta，有“安息”的意思，N.A.S.B.譯作refreshed（恢復精神、提神）。太11:28;啟6:11譯作“安息”；太26:45;可6:31;14:41譯作“安歇”；林前16:18譯作“快活”；林後7:13，譯作“暢快”。這句話很明顯地是指腓利門所行的善事。在此可見腓利門用愛心助人的結果，不但使眾聖徒的心暢快，更使使徒保羅的心大感快慰，顯然地他自己的心也必滿有喜樂。",
              "第三段為阿尼西母求情（8-21）",
              "一．保羅不用權柄（8-9）"
            ]
          }
        ],
        "title": "新約書信讀經講義",
        "author": "陳終道"
      }
    },
    "versions": {
      "ccb": {
        "version_id": "CCB",
        "version_name": "圣经当代译本",
        "lang": "chs",
        "text": "弟兄啊，你的爱心给我带来极大的喜乐和安慰，因为你使众圣徒感到欣慰。"
      },
      "cnv": {
        "version_id": "CNV",
        "version_name": "新譯本",
        "lang": "cht",
        "text": "弟兄啊，眾聖徒的心既然從你得到舒暢，我也因你的愛心，得到更大的喜樂和安慰。"
      },
      "cunp": {
        "version_id": "CUNP",
        "version_name": "和合本新標點（神版）",
        "lang": "cht",
        "text": "兄弟啊，我為你的愛心，大有快樂，大得安慰，因眾聖徒的心從你得了暢快。"
      },
      "nasb": {
        "version_id": "NASB",
        "version_name": "New American Standard Bible",
        "lang": "en",
        "text": "For I have come to have much joy and comfort in your love, because the hearts of the saints have been refreshed through you, brother."
      },
      "niv": {
        "version_id": "NIV",
        "version_name": "New International Version",
        "lang": "en",
        "text": "Your love has given me great joy and encouragement, because you, brother, have refreshed the hearts of the Lord’s people."
      },
      "nlt": {
        "version_id": "NLT",
        "version_name": "New Living Translation",
        "lang": "en",
        "text": "Your love has given me much joy and comfort, my brother, for your kindness has often refreshed the hearts of God’s people."
      }
    },
    "words": [
      {
        "id": "greek-5479",
        "translit": "charan",
        "lang": "greek",
        "greek": "χαρὰν",
        "pos": "N-AFS",
        "eng": "Joy"
      },
      {
        "id": "greek-1063",
        "translit": "gar",
        "lang": "greek",
        "greek": "γὰρ",
        "pos": "Conj",
        "eng": "for"
      },
      {
        "id": "greek-4183",
        "translit": "pollēn",
        "lang": "greek",
        "greek": "πολλὴν",
        "pos": "Adj-AFS",
        "eng": "great"
      },
      {
        "id": "greek-2192",
        "translit": "eschon",
        "lang": "greek",
        "greek": "ἔσχον",
        "pos": "V-AIA-1S",
        "punct": ",",
        "eng": "I have"
      },
      {
        "id": "greek-2532",
        "translit": "kai",
        "lang": "greek",
        "greek": "καὶ",
        "pos": "Conj",
        "eng": "and"
      },
      {
        "id": "greek-3874",
        "translit": "paraklēsin",
        "lang": "greek",
        "greek": "παράκλησιν",
        "pos": "N-AFS",
        "eng": "encouragement"
      },
      {
        "id": "greek-1909",
        "translit": "epi",
        "lang": "greek",
        "greek": "ἐπὶ",
        "pos": "Prep",
        "eng": "by occasion of"
      },
      {
        "id": "greek-3588",
        "translit": "tē",
        "lang": "greek",
        "greek": "τῇ",
        "pos": "Art-DFS",
        "eng": "the"
      },
      {
        "id": "greek-26",
        "translit": "agapē",
        "lang": "greek",
        "greek": "ἀγάπῃ",
        "pos": "N-DFS",
        "eng": "love"
      },
      {
        "id": "greek-4771",
        "translit": "sou",
        "lang": "greek",
        "greek": "σου",
        "pos": "PPro-G2S",
        "punct": ",",
        "eng": "of you"
      },
      {
        "id": "greek-3754",
        "translit": "hoti",
        "lang": "greek",
        "greek": "ὅτι",
        "pos": "Conj",
        "eng": "because"
      },
      {
        "id": "greek-3588",
        "translit": "ta",
        "lang": "greek",
        "greek": "τὰ",
        "pos": "Art-NNP",
        "eng": "the"
      },
      {
        "id": "greek-4698",
        "translit": "splanchna",
        "lang": "greek",
        "greek": "σπλάγχνα",
        "pos": "N-NNP",
        "eng": "hearts"
      },
      {
        "id": "greek-3588",
        "translit": "tōn",
        "lang": "greek",
        "greek": "τῶν",
        "pos": "Art-GMP",
        "eng": "of the"
      },
      {
        "id": "greek-40",
        "translit": "hagiōn",
        "lang": "greek",
        "greek": "ἁγίων",
        "pos": "Adj-GMP",
        "eng": "saints"
      },
      {
        "id": "greek-373",
        "translit": "anapepautai",
        "lang": "greek",
        "greek": "ἀναπέπαυται",
        "pos": "V-RIM/P-3S",
        "eng": "have been refreshed"
      },
      {
        "id": "greek-1223",
        "translit": "dia",
        "lang": "greek",
        "greek": "διὰ",
        "pos": "Prep",
        "eng": "by"
      },
      {
        "id": "greek-4771",
        "translit": "sou",
        "lang": "greek",
        "greek": "σοῦ",
        "pos": "PPro-G2S",
        "punct": ",",
        "eng": "you"
      },
      {
        "id": "greek-80",
        "translit": "adelphe",
        "lang": "greek",
        "greek": "ἀδελφέ",
        "pos": "N-VMS",
        "punct": ".",
        "eng": "brother"
      }
    ]
  }
}
